abstract_pandas/__init__.py
abstract_pandas/abstractLandManager.py
abstract_pandas/depriciated.py
abstract_pandas/excel_classes.py
abstract_pandas/excel_gui.py
abstract_pandas/excel_module.py
abstract_pandas/file_utils.py
abstract_pandas/functions.py
abstract_pandas/general_functions.py
abstract_pandas/location_functions.py
abstract_pandas/pdf_to_excel.py
abstract_pandas/proj_tools.py
abstract_pandas/query_tools.py
abstract_pandas/whites.py
abstract_pandas-0.0.44.16.dist-info/METADATA
abstract_pandas-0.0.44.16.dist-info/WHEEL
abstract_pandas-0.0.44.16.dist-info/top_level.txt
abstract_pandas-0.0.44.16.dist-info/RECORD
