Metadata-Version: 2.4
Name: abstract_pandas
Version: 0.0.44.16
Author: putkoff
Author-email: partners@abstractendeavors.com
Classifier: Development Status :: 3 - Alpha
Classifier: Intended Audience :: Developers
Classifier: License :: OSI Approved :: MIT License
Classifier: Programming Language :: Python :: 3
Classifier: Programming Language :: Python :: 3.11
Requires-Python: >=3.6
Requires-Dist: abstract_utilities
Requires-Dist: pandas
Requires-Dist: openpyxl
Requires-Dist: abstract_security
Requires-Dist: Werkzeug
Requires-Dist: odfpy
Requires-Dist: ezodf
Requires-Dist: lxml
Requires-Dist: geopandas
Requires-Dist: abstract_distances
Dynamic: author
Dynamic: author-email
Dynamic: classifier
Dynamic: description
Dynamic: description-content-type
Dynamic: requires-dist
Dynamic: requires-python
